[
  {
    "id": "region_001",
    "area": 87077,
    "center": [
      217,
      328
    ],
    "bbox": [
      29,
      21,
      377,
      494
    ],
    "status": "pending"
  },
  {
    "id": "region_054",
    "area": 5502,
    "center": [
      119,
      339
    ],
    "bbox": [
      61,
      283,
      99,
      98
    ],
    "status": "pending"
  },
  {
    "id": "region_053",
    "area": 5431,
    "center": [
      315,
      339
    ],
    "bbox": [
      275,
      283,
      99,
      98
    ],
    "status": "pending"
  },
  {
    "id": "region_044",
    "area": 2461,
    "center": [
      135,
      469
    ],
    "bbox": [
      106,
      438,
      57,
      60
    ],
    "status": "pending"
  },
  {
    "id": "region_040",
    "area": 2458,
    "center": [
      217,
      133
    ],
    "bbox": [
      201,
      90,
      34,
      90
    ],
    "status": "pending"
  },
  {
    "id": "region_043",
    "area": 2446,
    "center": [
      298,
      469
    ],
    "bbox": [
      272,
      438,
      57,
      59
    ],
    "status": "pending"
  },
  {
    "id": "region_042",
    "area": 1799,
    "center": [
      248,
      140
    ],
    "bbox": [
      220,
      33,
      58,
      206
    ],
    "status": "pending"
  },
  {
    "id": "region_041",
    "area": 1488,
    "center": [
      187,
      130
    ],
    "bbox": [
      160,
      35,
      54,
      176
    ],
    "status": "pending"
  },
  {
    "id": "region_049",
    "area": 1280,
    "center": [
      237,
      364
    ],
    "bbox": [
      228,
      331,
      20,
      69
    ],
    "status": "pending"
  },
  {
    "id": "region_050",
    "area": 1280,
    "center": [
      196,
      364
    ],
    "bbox": [
      187,
      331,
      20,
      69
    ],
    "status": "pending"
  },
  {
    "id": "region_056",
    "area": 828,
    "center": [
      195,
      239
    ],
    "bbox": [
      186,
      218,
      21,
      43
    ],
    "status": "pending"
  },
  {
    "id": "region_055",
    "area": 827,
    "center": [
      238,
      239
    ],
    "bbox": [
      228,
      218,
      21,
      43
    ],
    "status": "pending"
  },
  {
    "id": "region_047",
    "area": 745,
    "center": [
      268,
      400
    ],
    "bbox": [
      258,
      381,
      27,
      41
    ],
    "status": "pending"
  },
  {
    "id": "region_048",
    "area": 739,
    "center": [
      165,
      400
    ],
    "bbox": [
      151,
      381,
      26,
      41
    ],
    "status": "pending"
  },
  {
    "id": "region_032",
    "area": 719,
    "center": [
      217,
      272
    ],
    "bbox": [
      186,
      263,
      63,
      27
    ],
    "status": "pending"
  },
  {
    "id": "region_004",
    "area": 631,
    "center": [
      113,
      487
    ],
    "bbox": [
      97,
      452,
      52,
      58
    ],
    "status": "pending"
  },
  {
    "id": "region_003",
    "area": 600,
    "center": [
      318,
      490
    ],
    "bbox": [
      283,
      457,
      55,
      53
    ],
    "status": "pending"
  },
  {
    "id": "region_051",
    "area": 495,
    "center": [
      237,
      309
    ],
    "bbox": [
      228,
      297,
      21,
      26
    ],
    "status": "pending"
  },
  {
    "id": "region_017",
    "area": 491,
    "center": [
      250,
      407
    ],
    "bbox": [
      237,
      376,
      21,
      61
    ],
    "status": "pending"
  },
  {
    "id": "region_052",
    "area": 475,
    "center": [
      196,
      309
    ],
    "bbox": [
      187,
      297,
      20,
      26
    ],
    "status": "pending"
  },
  {
    "id": "region_045",
    "area": 374,
    "center": [
      316,
      394
    ],
    "bbox": [
      300,
      386,
      34,
      18
    ],
    "status": "pending"
  },
  {
    "id": "region_046",
    "area": 367,
    "center": [
      117,
      394
    ],
    "bbox": [
      101,
      386,
      34,
      17
    ],
    "status": "pending"
  },
  {
    "id": "region_020",
    "area": 358,
    "center": [
      173,
      364
    ],
    "bbox": [
      158,
      354,
      28,
      21
    ],
    "status": "pending"
  },
  {
    "id": "region_019",
    "area": 357,
    "center": [
      260,
      364
    ],
    "bbox": [
      249,
      355,
      28,
      20
    ],
    "status": "pending"
  },
  {
    "id": "region_018",
    "area": 319,
    "center": [
      181,
      397
    ],
    "bbox": [
      177,
      376,
      9,
      45
    ],
    "status": "pending"
  },
  {
    "id": "region_007",
    "area": 308,
    "center": [
      186,
      456
    ],
    "bbox": [
      178,
      437,
      16,
      41
    ],
    "status": "pending"
  },
  {
    "id": "region_012",
    "area": 262,
    "center": [
      322,
      412
    ],
    "bbox": [
      302,
      404,
      42,
      17
    ],
    "status": "pending"
  },
  {
    "id": "region_013",
    "area": 255,
    "center": [
      112,
      412
    ],
    "bbox": [
      92,
      404,
      41,
      17
    ],
    "status": "pending"
  },
  {
    "id": "region_016",
    "area": 255,
    "center": [
      71,
      399
    ],
    "bbox": [
      53,
      390,
      39,
      19
    ],
    "status": "pending"
  },
  {
    "id": "region_057",
    "area": 247,
    "center": [
      217,
      56
    ],
    "bbox": [
      210,
      46,
      16,
      20
    ],
    "status": "pending"
  },
  {
    "id": "region_006",
    "area": 238,
    "center": [
      217,
      462
    ],
    "bbox": [
      209,
      450,
      17,
      25
    ],
    "status": "pending"
  },
  {
    "id": "region_038",
    "area": 221,
    "center": [
      181,
      189
    ],
    "bbox": [
      173,
      181,
      20,
      18
    ],
    "status": "pending"
  },
  {
    "id": "region_037",
    "area": 219,
    "center": [
      252,
      190
    ],
    "bbox": [
      242,
      181,
      20,
      18
    ],
    "status": "pending"
  },
  {
    "id": "region_022",
    "area": 213,
    "center": [
      396,
      362
    ],
    "bbox": [
      392,
      346,
      9,
      35
    ],
    "status": "pending"
  },
  {
    "id": "region_021",
    "area": 202,
    "center": [
      37,
      362
    ],
    "bbox": [
      34,
      347,
      9,
      33
    ],
    "status": "pending"
  },
  {
    "id": "region_035",
    "area": 199,
    "center": [
      160,
      226
    ],
    "bbox": [
      157,
      210,
      9,
      34
    ],
    "status": "pending"
  },
  {
    "id": "region_029",
    "area": 178,
    "center": [
      175,
      300
    ],
    "bbox": [
      166,
      295,
      19,
      12
    ],
    "status": "pending"
  },
  {
    "id": "region_008",
    "area": 175,
    "center": [
      189,
      428
    ],
    "bbox": [
      181,
      421,
      18,
      16
    ],
    "status": "pending"
  },
  {
    "id": "region_033",
    "area": 171,
    "center": [
      264,
      250
    ],
    "bbox": [
      261,
      239,
      9,
      25
    ],
    "status": "pending"
  },
  {
    "id": "region_009",
    "area": 167,
    "center": [
      209,
      426
    ],
    "bbox": [
      201,
      418,
      15,
      18
    ],
    "status": "pending"
  },
  {
    "id": "region_005",
    "area": 165,
    "center": [
      247,
      462
    ],
    "bbox": [
      243,
      450,
      10,
      24
    ],
    "status": "pending"
  },
  {
    "id": "region_023",
    "area": 153,
    "center": [
      264,
      341
    ],
    "bbox": [
      258,
      333,
      15,
      19
    ],
    "status": "pending"
  },
  {
    "id": "region_010",
    "area": 151,
    "center": [
      293,
      423
    ],
    "bbox": [
      286,
      416,
      15,
      15
    ],
    "status": "pending"
  },
  {
    "id": "region_034",
    "area": 150,
    "center": [
      254,
      247
    ],
    "bbox": [
      250,
      238,
      9,
      20
    ],
    "status": "pending"
  },
  {
    "id": "region_024",
    "area": 147,
    "center": [
      169,
      341
    ],
    "bbox": [
      162,
      333,
      15,
      19
    ],
    "status": "pending"
  },
  {
    "id": "region_002",
    "area": 146,
    "center": [
      166,
      486
    ],
    "bbox": [
      157,
      479,
      19,
      17
    ],
    "status": "pending"
  },
  {
    "id": "region_011",
    "area": 144,
    "center": [
      140,
      423
    ],
    "bbox": [
      134,
      415,
      15,
      16
    ],
    "status": "pending"
  },
  {
    "id": "region_026",
    "area": 136,
    "center": [
      259,
      321
    ],
    "bbox": [
      256,
      310,
      7,
      24
    ],
    "status": "pending"
  },
  {
    "id": "region_027",
    "area": 136,
    "center": [
      175,
      321
    ],
    "bbox": [
      172,
      310,
      7,
      24
    ],
    "status": "pending"
  },
  {
    "id": "region_015",
    "area": 133,
    "center": [
      372,
      396
    ],
    "bbox": [
      363,
      390,
      20,
      13
    ],
    "status": "pending"
  },
  {
    "id": "region_031",
    "area": 133,
    "center": [
      253,
      294
    ],
    "bbox": [
      250,
      285,
      9,
      20
    ],
    "status": "pending"
  },
  {
    "id": "region_014",
    "area": 128,
    "center": [
      352,
      403
    ],
    "bbox": [
      343,
      398,
      21,
      11
    ],
    "status": "pending"
  },
  {
    "id": "region_036",
    "area": 118,
    "center": [
      217,
      192
    ],
    "bbox": [
      210,
      188,
      15,
      10
    ],
    "status": "pending"
  },
  {
    "id": "region_028",
    "area": 113,
    "center": [
      217,
      307
    ],
    "bbox": [
      209,
      304,
      18,
      8
    ],
    "status": "pending"
  },
  {
    "id": "region_039",
    "area": 108,
    "center": [
      241,
      180
    ],
    "bbox": [
      236,
      175,
      12,
      12
    ],
    "status": "pending"
  },
  {
    "id": "region_030",
    "area": 103,
    "center": [
      264,
      295
    ],
    "bbox": [
      261,
      288,
      8,
      17
    ],
    "status": "pending"
  },
  {
    "id": "region_025",
    "area": 100,
    "center": [
      223,
      333
    ],
    "bbox": [
      220,
      325,
      7,
      18
    ],
    "status": "pending"
  }
]